auto_editor/__init__.py
auto_editor/__main__.py
auto_editor-29.3.1.dist-info/licenses/LICENSE
auto_editor-29.3.1.dist-info/METADATA
auto_editor-29.3.1.dist-info/WHEEL
auto_editor-29.3.1.dist-info/entry_points.txt
auto_editor-29.3.1.dist-info/top_level.txt
auto_editor-29.3.1.dist-info/RECORD
