Metadata-Version: 2.4
Name: auto-editor
Version: 29.3.1
Summary: Auto-Editor: Effort free video editing!
Author-email: WyattBlue <wyattblue@auto-editor.com>
License-Expression: Unlicense
Project-URL: Bug Tracker, https://github.com/WyattBlue/auto-editor/discussions
Project-URL: Source Code, https://github.com/WyattBlue/auto-editor
Project-URL: homepage, https://auto-editor.com
Keywords: video,audio,media,editor,editing,processing,nonlinear,automatic,silence-detect,silence-removal,silence-speedup,motion-detection
Requires-Python: >=3.9
License-File: LICENSE
Dynamic: license-file
